nwlogger/__init__.py
nwlogger/constants.py
nwlogger/langchain_tracer.py
nwlogger/tracer.py
nwlogger/utils/__init__.py
nwlogger/utils/openai_info.py
nwlogger/utils/text_print.py
neurowave_logger-0.2.4b0.dist-info/METADATA
neurowave_logger-0.2.4b0.dist-info/WHEEL
neurowave_logger-0.2.4b0.dist-info/RECORD
