Metadata-Version: 2.1
Name: neurowave-logger
Version: 0.2.4b0
Summary: Log agent for Neurowave
License: MIT
Author: Neurowave AI
Author-email: it@neurowave.ai
Requires-Python: >=3.8
Classifier: License :: OSI Approved :: MIT License
Classifier: Programming Language :: Python :: 3
Classifier: Programming Language :: Python :: 3.8
Classifier: Programming Language :: Python :: 3.9
Classifier: Programming Language :: Python :: 3.10
Classifier: Programming Language :: Python :: 3.11
Classifier: Programming Language :: Python :: 3.12
Requires-Dist: langchain (==0.0.344)
Requires-Dist: loguru (==0.7.2)
Requires-Dist: openai (>=1.3.6)
Project-URL: homepage, https://github.com/neurowaveai/coeval_logger
